partitioner/__init__.py
partitioner/methods.py
partitioner/partitioner.py
partitioner-0.0.1.data/data/dictionaries/enwiktionary.txt
partitioner-0.0.1.data/data/qdumps/enwiktionary.json
partitioner-0.0.1.dist-info/DESCRIPTION.rst
partitioner-0.0.1.dist-info/METADATA
partitioner-0.0.1.dist-info/metadata.json
partitioner-0.0.1.dist-info/RECORD
partitioner-0.0.1.dist-info/top_level.txt
partitioner-0.0.1.dist-info/WHEEL
