Metadata-Version: 2.0
Name: partitioner
Version: 0.0.1
Summary: This is the text partitioner project for Python.
Home-page: http://jakerylandwilliams.github.io/partitioner/
Author: Jake Ryland Williams and Andy Reagan
Author-email: andy@andyreagan.com
License: Apache
Keywords: text partitioning natural language
Platform: UNKNOWN
Classifier: Development Status :: 3 - Alpha
Classifier: Intended Audience :: Developers
Classifier: Programming Language :: Python :: 2
Classifier: Programming Language :: Python :: 2.7
Classifier: Programming Language :: Python :: 3
Classifier: Programming Language :: Python :: 3.2
Classifier: Programming Language :: Python :: 3.3
Classifier: Programming Language :: Python :: 3.4
Classifier: Programming Language :: Python :: 3.5
